[
    {
        "id": 1,
        "nombre": "Cristian",
        "apellido": "Elias",
        "email": "cristiannicolas32@hotmail.com",
        "contraseña": "password",
        " rol": "Administrador",
        "imagen": "image"
    },
    {
        "id": 2,
        "nombre": "Jeaneth",
        "apellido": "Barrera",
        "email": "jeanette.barrera0710@gmail.com",
        "contraseña": "password",
        " rol": "Administrador",
        "imagen": "image"
    },
    {
        "id": 3,
        "nombre": "Lucas",
        "apellido": "Cordoba",
        "email": "lucascordoba2@hotmail.com",
        "contraseña": "123456789",
        "rol": "usuario",
        "imagen": "avatar-porDefecto.png"
    },
    {
        "id": 4,
        "nombre": "Yesica",
        "apellido": "Fiorentino",
        "email": "jesicafiore1@gmail.com",
        "contraseña": "password",
        " rol": "Administrador",
        "imagen": "image"
    },
    {
        "id": 5,
        "nombre": "Emiliano",
        "apellido": "Amarante",
        "email": "emiliano198218@gmail.com",
        "contraseña": "password",
        " rol": "Administrador",
        "imagen": "image"
    }
]